README.md
setup.py
avangate_rest_api_client/__init__.py
avangate_rest_api_client.egg-info/PKG-INFO
avangate_rest_api_client.egg-info/SOURCES.txt
avangate_rest_api_client.egg-info/dependency_links.txt
avangate_rest_api_client.egg-info/requires.txt
avangate_rest_api_client.egg-info/top_level.txt