Metadata-Version: 1.0
Name: avangate-rest-api-client
Version: 0.0.2
Summary: Python Client for Avangate REST API
Home-page: https://github.com/onursa/avangate_rest_api_client
Author: Onur Salgit
Author-email: mail@onur.org
License: MIT
Platform: UNKNOWN
